wrap_print/__init__.py
wrap_print-0.1.4.dist-info/METADATA
wrap_print-0.1.4.dist-info/WHEEL
wrap_print-0.1.4.dist-info/entry_points.txt
wrap_print-0.1.4.dist-info/top_level.txt
wrap_print-0.1.4.dist-info/RECORD
