Metadata-Version: 2.2
Name: wrap-print
Version: 0.1.4
Summary: A print tool that wraps text to a specified width.
Author-email: meebox <meebox@gmail.com>
Project-URL: repository, https://github.com/codemee/wrap_print
Project-URL: homepage, https://dev.to/codemee
Requires-Python: >=3.3
